NIR_preprocess/__init__.py
NIR_preprocess/compare_preprocessing.py
NIR_preprocess-0.0.5.dist-info/LICENSE.txt
NIR_preprocess-0.0.5.dist-info/METADATA
NIR_preprocess-0.0.5.dist-info/WHEEL
NIR_preprocess-0.0.5.dist-info/top_level.txt
NIR_preprocess-0.0.5.dist-info/RECORD
