Metadata-Version: 2.1
Name: NIR-preprocess
Version: 0.0.5
Summary: Function to evaluate impact of NIR pre-processing techniques on spectral data
Author: Giverny Robert, Ryan Gosselin
Author-email: giverny.robert@usherbrooke.ca, ryan.gosselin@usherbrooke.ca
License: UNKNOWN
Platform: UNKNOWN
Classifier: Programming Language :: Python :: 3
Classifier: License :: OSI Approved :: MIT License
Classifier: Operating System :: OS Independent
License-File: LICENSE.txt
